{
    "Reservations": [
        {
            "Groups": [],
            "Instances": [
                {
                    "AmiLaunchIndex": 0,
                    "ImageId": "ami-0f82752aa17ff8f5d",
                    "InstanceId": "i-08fd896a5d8f2c778",
                    "InstanceType": "t2.micro",
                    "KeyName": "MyKeyPair",
                    "LaunchTime": "2020-11-17T11:14:37.000Z",
                    "Monitoring": {
                        "State": "disabled"
                    },
                    "Placement": {
                        "AvailabilityZone": "us-east-1c",
                        "GroupName": "",
                        "Tenancy": "default"
                    },
                    "PrivateDnsName": "ip-172-31-85-248.ec2.internal",
                    "PrivateIpAddress": "172.31.85.248",
                    "ProductCodes": [],
                    "PublicDnsName": "ec2-34-230-37-90.compute-1.amazonaws.com",
                    "PublicIpAddress": "34.230.37.90",
                    "State": {
                        "Code": 16,
                        "Name": "running"
                    },
                    "StateTransitionReason": "",
                    "SubnetId": "subnet-5aef6b7b",
                    "VpcId": "vpc-8118d2fc",
                    "Architecture": "x86_64",
                    "BlockDeviceMappings": [
                        {
                            "DeviceName": "/dev/sda1",
                            "Ebs": {
                                "AttachTime": "2020-11-17T11:14:38.000Z",
                                "DeleteOnTermination": true,
                                "Status": "attached",
                                "VolumeId": "vol-0002d47d6e48f893d"
                            }
                        }
                    ],
                    "ClientToken": "f5722d96-7fcc-4f6d-8dff-bb8678c358f9",
                    "EbsOptimized": false,
                    "EnaSupport": true,
                    "Hypervisor": "xen",
                    "NetworkInterfaces": [
                        {
                            "Association": {
                                "IpOwnerId": "amazon",
                                "PublicDnsName": "ec2-34-230-37-90.compute-1.amazonaws.com",
                                "PublicIp": "34.230.37.90"
                            },
                            "Attachment": {
                                "AttachTime": "2020-11-17T11:14:37.000Z",
                                "AttachmentId": "eni-attach-015ab0102abe4b100",
                                "DeleteOnTermination": true,
                                "DeviceIndex": 0,
                                "Status": "attached"
                            },
                            "Description": "",
                            "Groups": [
                                {
                                    "GroupName": "unsw-9243-group22-minimoto-sg",
                                    "GroupId": "sg-0df1222527f5d49a1"
                                }
                            ],
                            "Ipv6Addresses": [],
                            "MacAddress": "12:0a:e4:14:68:8b",
                            "NetworkInterfaceId": "eni-0381b4647a39a0393",
                            "OwnerId": "071520043157",
                            "PrivateDnsName": "ip-172-31-85-248.ec2.internal",
                            "PrivateIpAddress": "172.31.85.248",
                            "PrivateIpAddresses": [
                                {
                                    "Association": {
                                        "IpOwnerId": "amazon",
                                        "PublicDnsName": "ec2-34-230-37-90.compute-1.amazonaws.com",
                                        "PublicIp": "34.230.37.90"
                                    },
                                    "Primary": true,
                                    "PrivateDnsName": "ip-172-31-85-248.ec2.internal",
                                    "PrivateIpAddress": "172.31.85.248"
                                }
                            ],
                            "SourceDestCheck": true,
                            "Status": "in-use",
                            "SubnetId": "subnet-5aef6b7b",
                            "VpcId": "vpc-8118d2fc",
                            "InterfaceType": "interface"
                        }
                    ],
                    "RootDeviceName": "/dev/sda1",
                    "RootDeviceType": "ebs",
                    "SecurityGroups": [
                        {
                            "GroupName": "unsw-9243-group22-minimoto-sg",
                            "GroupId": "sg-0df1222527f5d49a1"
                        }
                    ],
                    "SourceDestCheck": true,
                    "VirtualizationType": "hvm",
                    "CpuOptions": {
                        "CoreCount": 1,
                        "ThreadsPerCore": 1
                    },
                    "CapacityReservationSpecification": {
                        "CapacityReservationPreference": "open"
                    },
                    "HibernationOptions": {
                        "Configured": false
                    },
                    "MetadataOptions": {
                        "State": "applied",
                        "HttpTokens": "optional",
                        "HttpPutResponseHopLimit": 1,
                        "HttpEndpoint": "enabled"
                    }
                }
            ],
            "OwnerId": "071520043157",
            "ReservationId": "r-06a7376ed54db9c96"
        }
    ]
}
